{
  "type": "region",
  "name": "dashboard-js",
  "script": "./server/app.js",
  "error_file": "/sybase/logs/region_front/region-js_err.log",
  "out_file": "/sybase/logs/region_front/region-js_out.log",
  "merge_logs" : true,
  "log_date_format" : "YYYY-MM-DD_HH:mm:ss.SSS",
  "args": "",
  "env": {
    "sProfile_Application": "PROD",
    "NODE_TLS_REJECT_UNAUTHORIZED":"0",
    "bCompile_Application": "TRUE",
    "bDebug_Application": "FALSE",
    "bTest": "TRUE",

    "BackProxySession_Region":{
      "sSecret_BackProxySession_Region": "4a9mEAPAio6GbycjXWMJVA4h7WNtiC",
      "sKey1_BackProxySession_Region": "iEjjqJYLPOmSwZUIpNdk2lbLcnBgfD",
      "sKey2_BackProxySession_Region": "kY615vZh3IYo3tfSfiT6pNzDgKGuyv",
      "bSecure_BackProxySession_Region": "TRUE",
      "nLiveMS_BackProxySession_Region": 14400000
    },

    "Back_Region":{
      "sURL_Back_Region": "https://office.kievcity.gov.ua:443/wf/service",
      "sLogin_Back_Region": "system",
      "sPassword_Back_Region": "system",
      "nID_Server_Back_Region": 8
    },

    "Back_Central":{
      "sURL_Back_Central": "https://central.es.kievcity.gov.ua:443/wf/service",
      "sLogin_Back_Central": "system",
      "sPassword_Back_Central": "system"
    },

    "BackProxy_Region": {
      "sURL_BackProxy_Region": "https://office.kievcity.gov.ua:8444",
      "sKeyPath_BackProxy_Region": "cert/server.key",
      "sCertPath_BackProxy_Region": "cert/server.crt"
    },

    "BackSession_Region":{
      "nIdleMS_BackSession_Region": 3000,
      "nTimeoutMS_BackSession_Region": 3000,
      "nIntervalMS_BackSession_Region": 1000
    }
    , "LOG_DIR": "/home/gioc/.pm2/logs"
  }
}
